__init__.py
setup.py
weather_today.py
weather_today.egg-info/PKG-INFO
weather_today.egg-info/SOURCES.txt
weather_today.egg-info/dependency_links.txt
weather_today.egg-info/top_level.txt