Metadata-Version: 2.1
Name: weather-today
Version: 1.0
Summary: weather app
Home-page: UNKNOWN
Author: Ojas Mittal
Author-email: ojasfarm31@gmail.com
License: MIT
Platform: UNKNOWN
